loggsy/__init__.py
loggsy/logutils/__init__.py
loggsy/logutils/logutils.py
test/test.py
loggsy-0.1.3.dist-info/METADATA
loggsy-0.1.3.dist-info/WHEEL
loggsy-0.1.3.dist-info/top_level.txt
loggsy-0.1.3.dist-info/RECORD
