Metadata-Version: 2.4
Name: loggsy
Version: 0.1.3
Summary: 로그 활용 패키지
Author-email: kimyh <kim_yh663927@naver.com>
Classifier: Programming Language :: Python :: 3
Classifier: License :: OSI Approved :: MIT License
Classifier: Operating System :: OS Independent
Requires-Python: >=3.7
